{
  "section": "engagement",
  "description": "活跃数据 (新老用户)",
  "query": {
    "file": "sql/03_engagement_new_old_users.sql",
    "row_count": 26,
    "date_range": "20251110 ~ 20260208 (13周)",
    "latest_week": "20260208",
    "data_complete": true
  },
  "data": [
    {"周": "20251110", "用户类型（新老）": "新注册", "上周工具WAU": 40050},
    {"周": "20251110", "用户类型（新老）": "老用户", "上周工具WAU": 35961},
    {"周": "20251117", "用户类型（新老）": "老用户", "上周工具WAU": 35945},
    {"周": "20251117", "用户类型（新老）": "新注册", "上周工具WAU": 40270},
    {"周": "20251124", "用户类型（新老）": "老用户", "上周工具WAU": 34542},
    {"周": "20251124", "用户类型（新老）": "新注册", "上周工具WAU": 28277},
    {"周": "20251201", "用户类型（新老）": "老用户", "上周工具WAU": 32459},
    {"周": "20251201", "用户类型（新老）": "新注册", "上周工具WAU": 27196},
    {"周": "20251208", "用户类型（新老）": "新注册", "上周工具WAU": 23332},
    {"周": "20251208", "用户类型（新老）": "老用户", "上周工具WAU": 31463},
    {"周": "20251215", "用户类型（新老）": "新注册", "上周工具WAU": 20266},
    {"周": "20251215", "用户类型（新老）": "老用户", "上周工具WAU": 28704},
    {"周": "20251222", "用户类型（新老）": "新注册", "上周工具WAU": 25728},
    {"周": "20251222", "用户类型（新老）": "老用户", "上周工具WAU": 27510},
    {"周": "20251229", "用户类型（新老）": "新注册", "上周工具WAU": 24219},
    {"周": "20251229", "用户类型（新老）": "老用户", "上周工具WAU": 27615},
    {"周": "20260105", "用户类型（新老）": "新注册", "上周工具WAU": 26109},
    {"周": "20260105", "用户类型（新老）": "老用户", "上周工具WAU": 30761},
    {"周": "20260112", "用户类型（新老）": "新注册", "上周工具WAU": 26240},
    {"周": "20260112", "用户类型（新老）": "老用户", "上周工具WAU": 31493},
    {"周": "20260119", "用户类型（新老）": "老用户", "上周工具WAU": 30543},
    {"周": "20260119", "用户类型（新老）": "新注册", "上周工具WAU": 19293},
    {"周": "20260126", "用户类型（新老）": "老用户", "上周工具WAU": 31014},
    {"周": "20260126", "用户类型（新老）": "新注册", "上周工具WAU": 27570},
    {"周": "20260202", "用户类型（新老）": "新注册", "上周工具WAU": 22816},
    {"周": "20260202", "用户类型（新老）": "老用户", "上周工具WAU": 29942}
  ]
}